chromophile/__init__.py
chromophile/_cmaps.dat
chromophile-1.0.7.dist-info/LICENSE.txt
chromophile-1.0.7.dist-info/METADATA
chromophile-1.0.7.dist-info/WHEEL
chromophile-1.0.7.dist-info/top_level.txt
chromophile-1.0.7.dist-info/RECORD
