Metadata-Version: 2.1
Name: chromophile
Version: 1.0.7
Summary: Color maps for continuous quantitative data
Author-email: Kyle Hofmann <kyle.hofmann@gmail.com>
License: Creative Commons Legal Code
Project-URL: Homepage, https://github.com/kylehofmann/chromophile_dev
Project-URL: Bug Tracker, https://github.com/kylehofmann/chromophile_dev/issues
Classifier: Programming Language :: Python :: 3
Classifier: Development Status :: 5 - Production/Stable
Classifier: License :: CC0 1.0 Universal (CC0 1.0) Public Domain Dedication
Classifier: Intended Audience :: Science/Research
Classifier: Topic :: Multimedia :: Graphics
Classifier: Topic :: Scientific/Engineering :: Visualization
Classifier: Operating System :: OS Independent
Requires-Python: >=3.9
License-File: LICENSE.txt
